[
  {
    "name": "mvc-1",
    "url": "https://github.com/Sunyam-Lexicon-2024/mvc-1",
    "homepageUrl": "",
    "pushedAt": "2024-04-15T07:50:59Z",
    "diskUsage": 31802,
    "description": "A basic ASP.NET Core 8.0 MVC application",
    "commitTotal": 16
  },
  {
    "name": "frontend-api",
    "url": "https://github.com/Sunyam-Lexicon-2024/frontend-api",
    "homepageUrl": "https://sunyam-lexicon-2024.github.io/frontend-api/",
    "pushedAt": "2024-04-10T07:28:11Z",
    "diskUsage": 164,
    "description": "A small frontend to test API interaction",
    "commitTotal": 13
  },
  {
    "name": "personell-registry-app",
    "url": "https://github.com/Sunyam-Lexicon-2024/personell-registry-app",
    "homepageUrl": "",
    "pushedAt": "2024-04-10T07:30:34Z",
    "diskUsage": 3,
    "description": "A small application built to simulate registration of personell",
    "commitTotal": 2
  },
  {
    "name": "oop-basics-extras-1",
    "url": "https://github.com/Sunyam-Lexicon-2024/oop-basics-extras-1",
    "homepageUrl": "",
    "pushedAt": "2024-04-10T07:34:10Z",
    "diskUsage": 3,
    "description": "Some small extra tests for OOP in C#",
    "commitTotal": 3
  },
  {
    "name": ".github",
    "url": "https://github.com/Sunyam-Lexicon-2024/.github",
    "homepageUrl": null,
    "pushedAt": "2024-04-11T12:50:08Z",
    "diskUsage": 2,
    "description": "Organization Resources Repository",
    "commitTotal": 2
  },
  {
    "name": "memory-management",
    "url": "https://github.com/Sunyam-Lexicon-2024/memory-management",
    "homepageUrl": "",
    "pushedAt": "2024-04-10T07:32:32Z",
    "diskUsage": 64,
    "description": "A small exercise in C# memory management",
    "commitTotal": 3
  },
  {
    "name": "oop-basics-extras-2",
    "url": "https://github.com/Sunyam-Lexicon-2024/oop-basics-extras-2",
    "homepageUrl": "",
    "pushedAt": "2024-04-10T07:34:29Z",
    "diskUsage": 7,
    "description": "Some small extra tests for OOP in C#, part deux!",
    "commitTotal": 3
  },
  {
    "name": "frontend-javascript",
    "url": "https://github.com/Sunyam-Lexicon-2024/frontend-javascript",
    "homepageUrl": "https://sunyam-lexicon-2024.github.io/frontend-javascript/",
    "pushedAt": "2024-04-10T07:28:48Z",
    "diskUsage": 309,
    "description": "A small frontend to test JavaScript",
    "commitTotal": 24
  },
  {
    "name": "garage-1.0",
    "url": "https://github.com/Sunyam-Lexicon-2024/garage-1.0",
    "homepageUrl": "",
    "pushedAt": "2024-04-10T07:29:59Z",
    "diskUsage": 2318,
    "description": "A small application for handling registration, deregistration and data of Vehicles stored in select Garages.",
    "commitTotal": 5
  },
  {
    "name": "oop-basics",
    "url": "https://github.com/Sunyam-Lexicon-2024/oop-basics",
    "homepageUrl": "",
    "pushedAt": "2024-04-10T07:33:45Z",
    "diskUsage": 7,
    "description": "Some small extra tests for OOP in C#",
    "commitTotal": 3
  }
]